{
  "FactionId": 0,
  "BuildingType": 18,
  "Quality": 8,
  "NameSeed": 0,
  "RmbSubRecord": {
    "XPos": 320,
    "ZPos": 1728,
    "YRotation": 1536,
    "Exterior": {
      "Header": {
        "Num3dObjectRecords": 1,
        "NumFlatObjectRecords": 0,
        "NumSection3Records": 0,
        "NumPeopleRecords": 0,
        "NumDoorRecords": 0
      },
      "Block3dObjectRecords": [
        {
          "ModelId": "136",
          "ModelIdNum": 136,
          "ObjectType": 4,
          "XPos": 0,
          "YPos": 0,
          "ZPos": 0,
          "XRotation": 0,
          "YRotation": 0,
          "ZRotation": 0
        }
      ],
      "BlockFlatObjectRecords": [],
      "BlockSection3Records": [],
      "BlockPeopleRecords": [],
      "BlockDoorRecords": []
    },
    "Interior": {
      "Header": {
        "Num3dObjectRecords": 25,
        "NumFlatObjectRecords": 10,
        "NumSection3Records": 28,
        "NumPeopleRecords": 1,
        "NumDoorRecords": 1
      },
      "Block3dObjectRecords": [
        {
          "ModelId": "28004",
          "ModelIdNum": 28004,
          "ObjectType": 13,
          "XPos": 0,
          "YPos": -159,
          "ZPos": 0,
          "XRotation": 0,
          "YRotation": 0,
          "ZRotation": 0
        },
        {
          "ModelId": "31019",
          "ModelIdNum": 31019,
          "ObjectType": 13,
          "XPos": 125,
          "YPos": -63,
          "ZPos": 0,
          "XRotation": 0,
          "YRotation": -512,
          "ZRotation": 0
        },
        {
          "ModelId": "31026",
          "ModelIdNum": 31026,
          "ObjectType": 13,
          "XPos": 0,
          "YPos": -63,
          "ZPos": 253,
          "XRotation": 0,
          "YRotation": -1536,
          "ZRotation": 0
        },
        {
          "ModelId": "31006",
          "ModelIdNum": 31006,
          "ObjectType": 13,
          "XPos": 125,
          "YPos": -63,
          "ZPos": -253,
          "XRotation": 0,
          "YRotation": 0,
          "ZRotation": 0
        },
        {
          "ModelId": "31018",
          "ModelIdNum": 31018,
          "ObjectType": 13,
          "XPos": 125,
          "YPos": -63,
          "ZPos": 128,
          "XRotation": 0,
          "YRotation": -1536,
          "ZRotation": 0
        },
        {
          "ModelId": "31025",
          "ModelIdNum": 31025,
          "ObjectType": 13,
          "XPos": 0,
          "YPos": -63,
          "ZPos": -128,
          "XRotation": 0,
          "YRotation": -1536,
          "ZRotation": 0
        },
        {
          "ModelId": "31025",
          "ModelIdNum": 31025,
          "ObjectType": 13,
          "XPos": 0,
          "YPos": -63,
          "ZPos": 0,
          "XRotation": 0,
          "YRotation": -1536,
          "ZRotation": 0
        },
        {
          "ModelId": "31025",
          "ModelIdNum": 31025,
          "ObjectType": 13,
          "XPos": 0,
          "YPos": -63,
          "ZPos": 128,
          "XRotation": 0,
          "YRotation": -1536,
          "ZRotation": 0
        },
        {
          "ModelId": "41109",
          "ModelIdNum": 41109,
          "ObjectType": 3,
          "XPos": 0,
          "YPos": 2,
          "ZPos": -250,
          "XRotation": 0,
          "YRotation": -2046,
          "ZRotation": 0
        },
        {
          "ModelId": "41108",
          "ModelIdNum": 41108,
          "ObjectType": 3,
          "XPos": 0,
          "YPos": 2,
          "ZPos": -104,
          "XScale": 1.019467,
          "ZScale": 1.014101,
          "XRotation": 0,
          "YRotation": -509,
          "ZRotation": 0
        },
        {
          "ModelId": "41106",
          "ModelIdNum": 41106,
          "ObjectType": 3,
          "XPos": -40,
          "YPos": 2,
          "ZPos": -104,
          "XRotation": 0,
          "YRotation": -509,
          "ZRotation": 0
        },
        {
          "ModelId": "41100",
          "ModelIdNum": 41100,
          "ObjectType": 3,
          "XPos": -80,
          "YPos": 2,
          "ZPos": -256,
          "XRotation": 0,
          "YRotation": -251,
          "ZRotation": 0
        },
        {
          "ModelId": "41100",
          "ModelIdNum": 41100,
          "ObjectType": 3,
          "XPos": 24,
          "YPos": 2,
          "ZPos": -208,
          "XRotation": 0,
          "YRotation": -1083,
          "ZRotation": 0
        },
        {
          "ModelId": "41409",
          "ModelIdNum": 41409,
          "ObjectType": 3,
          "XPos": 128,
          "YPos": 2,
          "ZPos": 206,
          "XRotation": 0,
          "YRotation": 0,
          "ZRotation": 0
        },
        {
          "ModelId": "3020",
          "ModelIdNum": 3020,
          "ObjectType": 13,
          "XPos": -130,
          "YPos": 1,
          "ZPos": -125,
          "XRotation": 0,
          "YRotation": -1024,
          "ZRotation": 0
        },
        {
          "ModelId": "1024",
          "ModelIdNum": 1024,
          "ObjectType": 13,
          "XPos": -128,
          "YPos": 0,
          "ZPos": 251,
          "ZScale": 1.002,
          "XRotation": 0,
          "YRotation": -511,
          "ZRotation": 0
        },
        {
          "ModelId": "2024",
          "ModelIdNum": 2024,
          "ObjectType": 13,
          "XPos": -128,
          "YPos": 2,
          "ZPos": 257,
          "XRotation": 0,
          "YRotation": -512,
          "ZRotation": 0
        },
        {
          "ModelId": "3004",
          "ModelIdNum": 3004,
          "ObjectType": 13,
          "XPos": -188,
          "YPos": -63,
          "ZPos": 246,
          "XRotation": 0,
          "YRotation": -1024,
          "ZRotation": 0
        },
        {
          "ModelId": "3004",
          "ModelIdNum": 3004,
          "ObjectType": 13,
          "XPos": -188,
          "YPos": -63,
          "ZPos": -240,
          "XRotation": 0,
          "YRotation": -1024,
          "ZRotation": 0
        },
        {
          "ModelId": "1000",
          "ModelIdNum": 1000,
          "ObjectType": 13,
          "XPos": 0,
          "YPos": 0,
          "ZPos": -256,
          "XRotation": 0,
          "YRotation": -512,
          "ZRotation": 0
        },
        {
          "ModelId": "3004",
          "ModelIdNum": 3004,
          "ObjectType": 13,
          "XPos": -130,
          "YPos": -64,
          "ZPos": -314,
          "XRotation": 0,
          "YRotation": -512,
          "ZRotation": 0
        },
        {
          "ModelId": "3018",
          "ModelIdNum": 3018,
          "ObjectType": 13,
          "XPos": -4,
          "YPos": -64,
          "ZPos": -314,
          "XRotation": 0,
          "YRotation": -512,
          "ZRotation": 0
        },
        {
          "ModelId": "4004",
          "ModelIdNum": 4004,
          "ObjectType": 13,
          "XPos": -67,
          "YPos": -62,
          "ZPos": 64,
          "XScale": 1.1097,
          "XRotation": 0,
          "YRotation": -511,
          "ZRotation": 0
        },
        {
          "ModelId": "4004",
          "ModelIdNum": 4004,
          "ObjectType": 13,
          "XPos": -59,
          "YPos": -62,
          "ZPos": 64,
          "XScale": 1.1097,
          "XRotation": 0,
          "YRotation": -1536,
          "ZRotation": 0
        },
        {
          "ModelId": "4004",
          "ModelIdNum": 4004,
          "ObjectType": 13,
          "XPos": -67,
          "YPos": -62,
          "ZPos": 192,
          "XScale": 1.1097,
          "XRotation": 0,
          "YRotation": -511,
          "ZRotation": 0
        },
        {
          "ModelId": "4004",
          "ModelIdNum": 4004,
          "ObjectType": 13,
          "XPos": -59,
          "YPos": -62,
          "ZPos": 192,
          "XScale": 1.1097,
          "XRotation": 0,
          "YRotation": -1536,
          "ZRotation": 0
        },
        {
          "ModelId": "62319",
          "ModelIdNum": 62319,
          "ObjectType": 0,
          "XPos": -192,
          "YPos": -64,
          "ZPos": -306,
          "XScale": 1.047973,
          "XRotation": 0,
          "YRotation": 0,
          "ZRotation": -512
        },
        {
          "ModelId": "62319",
          "ModelIdNum": 62319,
          "ObjectType": 0,
          "XPos": -192,
          "YPos": -62,
          "ZPos": 310,
          "XScale": 1.0931,
          "XRotation": 0,
          "YRotation": 0,
          "ZRotation": -512
        },
        {
          "ModelId": "3004",
          "ModelIdNum": 3004,
          "ObjectType": 13,
          "XPos": -128,
          "YPos": -62,
          "ZPos": 314,
          "YScale": 1.0136,
          "XRotation": 0,
          "YRotation": -1536,
          "ZRotation": 0
        },
        {
          "ModelId": "2000",
          "ModelIdNum": 2000,
          "ObjectType": 13,
          "XPos": -1,
          "YPos": -126,
          "ZPos": -254,
          "XRotation": 0,
          "YRotation": -512,
          "ZRotation": 0
        },
        {
          "ModelId": "4004",
          "ModelIdNum": 4004,
          "ObjectType": 13,
          "XPos": -67,
          "YPos": -62,
          "ZPos": -64,
          "XScale": 1.1097,
          "XRotation": 0,
          "YRotation": -511,
          "ZRotation": 0
        },
        {
          "ModelId": "4004",
          "ModelIdNum": 4004,
          "ObjectType": 13,
          "XPos": -59,
          "YPos": -62,
          "ZPos": -64,
          "XScale": 1.1097,
          "XRotation": 0,
          "YRotation": -1536,
          "ZRotation": 0
        },
        {
          "ModelId": "4004",
          "ModelIdNum": 4004,
          "ObjectType": 13,
          "XPos": -67,
          "YPos": -62,
          "ZPos": -192,
          "XScale": 1.1097,
          "XRotation": 0,
          "YRotation": -511,
          "ZRotation": 0
        },
        {
          "ModelId": "4004",
          "ModelIdNum": 4004,
          "ObjectType": 13,
          "XPos": -59,
          "YPos": -62,
          "ZPos": -192,
          "XScale": 1.1097,
          "XRotation": 0,
          "YRotation": -1536,
          "ZRotation": 0
        },
        {
          "ModelId": "4004",
          "ModelIdNum": 4004,
          "ObjectType": 13,
          "XPos": -68,
          "YPos": -64,
          "ZPos": -311,
          "XRotation": 0,
          "YRotation": -1024,
          "ZRotation": 0
        },
        {
          "ModelId": "4004",
          "ModelIdNum": 4004,
          "ObjectType": 13,
          "XPos": 60,
          "YPos": -64,
          "ZPos": -311,
          "XRotation": 0,
          "YRotation": -1024,
          "ZRotation": 0
        },
        {
          "ModelId": "4004",
          "ModelIdNum": 4004,
          "ObjectType": 13,
          "XPos": -68,
          "YPos": -62,
          "ZPos": 311,
          "YScale": 1.0144,
          "XRotation": 0,
          "YRotation": 0,
          "ZRotation": 0
        },
        {
          "ModelId": "4004",
          "ModelIdNum": 4004,
          "ObjectType": 13,
          "XPos": 60,
          "YPos": -62,
          "ZPos": -192,
          "XScale": 1.1097,
          "XRotation": 0,
          "YRotation": -511,
          "ZRotation": 0
        },
        {
          "ModelId": "4004",
          "ModelIdNum": 4004,
          "ObjectType": 13,
          "XPos": 68,
          "YPos": -62,
          "ZPos": -192,
          "XScale": 1.1097,
          "XRotation": 0,
          "YRotation": -1536,
          "ZRotation": 0
        },
        {
          "ModelId": "3004",
          "ModelIdNum": 3004,
          "ObjectType": 13,
          "XPos": 122,
          "YPos": -64,
          "ZPos": -66,
          "XRotation": 0,
          "YRotation": -1536,
          "ZRotation": 0
        },
        {
          "ModelId": "3018",
          "ModelIdNum": 3018,
          "ObjectType": 13,
          "XPos": 186,
          "YPos": -64,
          "ZPos": -130,
          "XRotation": 0,
          "YRotation": 0,
          "ZRotation": 0
        },
        {
          "ModelId": "1000",
          "ModelIdNum": 1000,
          "ObjectType": 13,
          "XPos": 128,
          "YPos": 0,
          "ZPos": -126,
          "ZScale": 1.033,
          "XRotation": 0,
          "YRotation": 0,
          "ZRotation": 0
        },
        {
          "ModelId": "4004",
          "ModelIdNum": 4004,
          "ObjectType": 13,
          "XPos": 182,
          "YPos": -64,
          "ZPos": -71,
          "ZScale": 1.435709,
          "XRotation": 0,
          "YRotation": 0,
          "ZRotation": 0
        },
        {
          "ModelId": "2000",
          "ModelIdNum": 2000,
          "ObjectType": 13,
          "XPos": 127,
          "YPos": -126,
          "ZPos": -128,
          "XRotation": 0,
          "YRotation": -512,
          "ZRotation": 0
        },
        {
          "ModelId": "4000",
          "ModelIdNum": 4000,
          "ObjectType": 13,
          "XPos": 65,
          "YPos": -62,
          "ZPos": -64,
          "YScale": 1.0268,
          "XRotation": 0,
          "YRotation": -1536,
          "ZRotation": 0
        },
        {
          "ModelId": "4004",
          "ModelIdNum": 4004,
          "ObjectType": 13,
          "XPos": 183,
          "YPos": -64,
          "ZPos": -190,
          "ZScale": 1.435709,
          "XRotation": 0,
          "YRotation": -511,
          "ZRotation": 0
        },
        {
          "ModelId": "45081",
          "ModelIdNum": 45081,
          "ObjectType": 0,
          "XPos": 164,
          "YPos": -54,
          "ZPos": -284,
          "XScale": 0.5,
          "YScale": 0.739072,
          "XRotation": 0,
          "YRotation": -512,
          "ZRotation": -511
        },
        {
          "ModelId": "41117",
          "ModelIdNum": 41117,
          "ObjectType": 3,
          "XPos": 170,
          "YPos": 7,
          "ZPos": -253,
          "XScale": 0.9238399,
          "ZScale": 0.4840072,
          "XRotation": 0,
          "YRotation": -1536,
          "ZRotation": 0
        },
        {
          "ModelId": "45076",
          "ModelIdNum": 45076,
          "ObjectType": 0,
          "XPos": 175,
          "YPos": -15,
          "ZPos": -254,
          "XScale": 0.9818566,
          "ZScale": 0.3786712,
          "XRotation": 0,
          "YRotation": -511,
          "ZRotation": 0
        },
        {
          "ModelId": "45081",
          "ModelIdNum": 45081,
          "ObjectType": 0,
          "XPos": 162,
          "YPos": -60,
          "ZPos": -295,
          "YScale": 0.9691583,
          "XRotation": 0,
          "YRotation": -512,
          "ZRotation": -512
        },
        {
          "ModelId": "45129",
          "ModelIdNum": 45129,
          "ObjectType": 0,
          "XPos": 171,
          "YPos": -2,
          "ZPos": -330,
          "XScale": 1.2,
          "YScale": 1.777394,
          "ZScale": 4.22892,
          "XRotation": 0,
          "YRotation": -512,
          "ZRotation": -512
        },
        {
          "ModelId": "41105",
          "ModelIdNum": 41105,
          "ObjectType": 0,
          "XPos": 168,
          "YPos": -16,
          "ZPos": -128,
          "XScale": 1.178657,
          "XRotation": 0,
          "YRotation": -511,
          "ZRotation": 0
        },
        {
          "ModelId": "41037",
          "ModelIdNum": 41037,
          "ObjectType": 0,
          "XPos": -152,
          "YPos": -36,
          "ZPos": -301,
          "XRotation": 0,
          "YRotation": 0,
          "ZRotation": 0
        },
        {
          "ModelId": "41124",
          "ModelIdNum": 41124,
          "ObjectType": 0,
          "XPos": 104,
          "YPos": -33,
          "ZPos": -78,
          "XRotation": 0,
          "YRotation": -1024,
          "ZRotation": 0
        },
        {
          "ModelId": "51115",
          "ModelIdNum": 51115,
          "ObjectType": 0,
          "XPos": -172,
          "YPos": -50,
          "ZPos": -2,
          "XRotation": 0,
          "YRotation": -1536,
          "ZRotation": 0
        },
        {
          "ModelId": "41811",
          "ModelIdNum": 41811,
          "ObjectType": 3,
          "XPos": 156,
          "YPos": 0,
          "ZPos": 160,
          "XRotation": 0,
          "YRotation": -1536,
          "ZRotation": 0
        },
        {
          "ModelId": "41013",
          "ModelIdNum": 41013,
          "ObjectType": 3,
          "XPos": -130,
          "YPos": 1,
          "ZPos": 304,
          "XRotation": 0,
          "YRotation": 0,
          "ZRotation": 0
        },
        {
          "ModelId": "41007",
          "ModelIdNum": 41007,
          "ObjectType": 3,
          "XPos": 24,
          "YPos": 46,
          "ZPos": 302,
          "XRotation": 0,
          "YRotation": -1024,
          "ZRotation": 0
        },
        {
          "ModelId": "41007",
          "ModelIdNum": 41007,
          "ObjectType": 3,
          "XPos": -30,
          "YPos": 46,
          "ZPos": 302,
          "XRotation": 0,
          "YRotation": -1024,
          "ZRotation": 0
        },
        {
          "ModelId": "41125",
          "ModelIdNum": 41125,
          "ObjectType": 0,
          "XPos": -86,
          "YPos": -142,
          "ZPos": 120,
          "XRotation": 0,
          "YRotation": -113,
          "ZRotation": 0
        },
        {
          "ModelId": "41018",
          "ModelIdNum": 41018,
          "ObjectType": 0,
          "XPos": -180,
          "YPos": -37,
          "ZPos": -16,
          "XRotation": 0,
          "YRotation": -512,
          "ZRotation": 0
        },
        {
          "ModelId": "41113",
          "ModelIdNum": 41113,
          "ObjectType": 0,
          "XPos": -180,
          "YPos": -11,
          "ZPos": 28,
          "XRotation": 0,
          "YRotation": 0,
          "ZRotation": 0
        },
        {
          "ModelId": "69465",
          "ModelIdNum": 69465,
          "ObjectType": 0,
          "XPos": 174,
          "YPos": 0,
          "ZPos": -254,
          "XScale": 0.33138,
          "YScale": 0.6,
          "ZScale": 0.9,
          "XRotation": 0,
          "YRotation": 0,
          "ZRotation": 0
        },
        {
          "ModelId": "45110",
          "ModelIdNum": 45110,
          "ObjectType": 0,
          "XPos": 30,
          "YPos": -228,
          "ZPos": -122,
          "YScale": 0.9447299,
          "XRotation": 0,
          "YRotation": -1024,
          "ZRotation": -170
        },
        {
          "ModelId": "45110",
          "ModelIdNum": 45110,
          "ObjectType": 0,
          "XPos": 30,
          "YPos": -222,
          "ZPos": -122,
          "YScale": 1.51672,
          "ZScale": 1.2,
          "XRotation": 0,
          "YRotation": 0,
          "ZRotation": -84
        },
        {
          "ModelId": "45110",
          "ModelIdNum": 45110,
          "ObjectType": 0,
          "XPos": 118,
          "YPos": -224,
          "ZPos": -122,
          "YScale": 2.78978,
          "ZScale": 1.3,
          "XRotation": 0,
          "YRotation": 0,
          "ZRotation": -511
        },
        {
          "ModelId": "45110",
          "ModelIdNum": 45110,
          "ObjectType": 0,
          "XPos": -26,
          "YPos": -222,
          "ZPos": -122,
          "YScale": 1.11605,
          "ZScale": 1.2,
          "XRotation": 0,
          "YRotation": 0,
          "ZRotation": -169
        },
        {
          "ModelId": "45110",
          "ModelIdNum": 45110,
          "ObjectType": 0,
          "XPos": -28,
          "YPos": -228,
          "ZPos": -122,
          "YScale": 1.39692,
          "XRotation": 0,
          "YRotation": -1024,
          "ZRotation": -85
        },
        {
          "ModelId": "45110",
          "ModelIdNum": 45110,
          "ObjectType": 0,
          "XPos": 30,
          "YPos": -224,
          "ZPos": 2,
          "YScale": 0.9447299,
          "XRotation": 0,
          "YRotation": -1024,
          "ZRotation": -170
        },
        {
          "ModelId": "45110",
          "ModelIdNum": 45110,
          "ObjectType": 0,
          "XPos": 30,
          "YPos": -222,
          "ZPos": 2,
          "YScale": 1.51672,
          "ZScale": 1.2,
          "XRotation": 0,
          "YRotation": 0,
          "ZRotation": -84
        },
        {
          "ModelId": "45110",
          "ModelIdNum": 45110,
          "ObjectType": 0,
          "XPos": 118,
          "YPos": -224,
          "ZPos": 2,
          "YScale": 2.78978,
          "ZScale": 1.3,
          "XRotation": 0,
          "YRotation": 0,
          "ZRotation": -511
        },
        {
          "ModelId": "45110",
          "ModelIdNum": 45110,
          "ObjectType": 0,
          "XPos": -26,
          "YPos": -222,
          "ZPos": 2,
          "YScale": 1.11605,
          "ZScale": 1.2,
          "XRotation": 0,
          "YRotation": 0,
          "ZRotation": -169
        },
        {
          "ModelId": "45110",
          "ModelIdNum": 45110,
          "ObjectType": 0,
          "XPos": -28,
          "YPos": -228,
          "ZPos": 2,
          "YScale": 1.39692,
          "XRotation": 0,
          "YRotation": -1024,
          "ZRotation": -85
        },
        {
          "ModelId": "45110",
          "ModelIdNum": 45110,
          "ObjectType": 0,
          "XPos": 30,
          "YPos": -228,
          "ZPos": 124,
          "YScale": 0.9447299,
          "XRotation": 0,
          "YRotation": -1024,
          "ZRotation": -170
        },
        {
          "ModelId": "45110",
          "ModelIdNum": 45110,
          "ObjectType": 0,
          "XPos": 30,
          "YPos": -222,
          "ZPos": 124,
          "YScale": 1.51672,
          "ZScale": 1.2,
          "XRotation": 0,
          "YRotation": 0,
          "ZRotation": -84
        },
        {
          "ModelId": "45110",
          "ModelIdNum": 45110,
          "ObjectType": 0,
          "XPos": 118,
          "YPos": -224,
          "ZPos": 124,
          "YScale": 2.78978,
          "ZScale": 1.3,
          "XRotation": 0,
          "YRotation": 0,
          "ZRotation": -511
        },
        {
          "ModelId": "45110",
          "ModelIdNum": 45110,
          "ObjectType": 0,
          "XPos": -26,
          "YPos": -222,
          "ZPos": 124,
          "YScale": 1.11605,
          "ZScale": 1.2,
          "XRotation": 0,
          "YRotation": 0,
          "ZRotation": -169
        },
        {
          "ModelId": "45110",
          "ModelIdNum": 45110,
          "ObjectType": 0,
          "XPos": -28,
          "YPos": -228,
          "ZPos": 124,
          "YScale": 1.39692,
          "XRotation": 0,
          "YRotation": -1024,
          "ZRotation": -85
        },
        {
          "ModelId": "45110",
          "ModelIdNum": 45110,
          "ObjectType": 0,
          "XPos": 30,
          "YPos": -228,
          "ZPos": 250,
          "YScale": 0.9447299,
          "XRotation": 0,
          "YRotation": -1024,
          "ZRotation": -170
        },
        {
          "ModelId": "45110",
          "ModelIdNum": 45110,
          "ObjectType": 0,
          "XPos": 30,
          "YPos": -222,
          "ZPos": 250,
          "YScale": 1.51672,
          "ZScale": 1.2,
          "XRotation": 0,
          "YRotation": 0,
          "ZRotation": -84
        },
        {
          "ModelId": "45110",
          "ModelIdNum": 45110,
          "ObjectType": 0,
          "XPos": 118,
          "YPos": -224,
          "ZPos": 250,
          "YScale": 2.78978,
          "ZScale": 1.3,
          "XRotation": 0,
          "YRotation": 0,
          "ZRotation": -511
        },
        {
          "ModelId": "45110",
          "ModelIdNum": 45110,
          "ObjectType": 0,
          "XPos": -26,
          "YPos": -222,
          "ZPos": 250,
          "YScale": 1.11605,
          "ZScale": 1.2,
          "XRotation": 0,
          "YRotation": 0,
          "ZRotation": -169
        },
        {
          "ModelId": "45110",
          "ModelIdNum": 45110,
          "ObjectType": 0,
          "XPos": -28,
          "YPos": -228,
          "ZPos": 250,
          "YScale": 1.39692,
          "XRotation": 0,
          "YRotation": -1024,
          "ZRotation": -85
        },
        {
          "ModelId": "45110",
          "ModelIdNum": 45110,
          "ObjectType": 0,
          "XPos": 30,
          "YPos": -228,
          "ZPos": -252,
          "YScale": 0.9447299,
          "XRotation": 0,
          "YRotation": -1024,
          "ZRotation": -170
        },
        {
          "ModelId": "45110",
          "ModelIdNum": 45110,
          "ObjectType": 0,
          "XPos": 30,
          "YPos": -222,
          "ZPos": -252,
          "YScale": 1.51672,
          "ZScale": 1.2,
          "XRotation": 0,
          "YRotation": 0,
          "ZRotation": -84
        },
        {
          "ModelId": "45110",
          "ModelIdNum": 45110,
          "ObjectType": 0,
          "XPos": 118,
          "YPos": -224,
          "ZPos": -252,
          "YScale": 2.78978,
          "ZScale": 1.3,
          "XRotation": 0,
          "YRotation": 0,
          "ZRotation": -511
        },
        {
          "ModelId": "45110",
          "ModelIdNum": 45110,
          "ObjectType": 0,
          "XPos": -26,
          "YPos": -222,
          "ZPos": -252,
          "YScale": 1.11605,
          "ZScale": 1.2,
          "XRotation": 0,
          "YRotation": 0,
          "ZRotation": -169
        },
        {
          "ModelId": "45110",
          "ModelIdNum": 45110,
          "ObjectType": 0,
          "XPos": -28,
          "YPos": -228,
          "ZPos": -252,
          "YScale": 1.39692,
          "XRotation": 0,
          "YRotation": -1024,
          "ZRotation": -85
        },
        {
          "ModelId": "41009",
          "ModelIdNum": 41009,
          "ObjectType": 0,
          "XPos": 74,
          "YPos": -151,
          "ZPos": -159,
          "XRotation": 0,
          "YRotation": 0,
          "ZRotation": 0
        },
        {
          "ModelId": "42076",
          "ModelIdNum": 42076,
          "ObjectType": 0,
          "XPos": -89,
          "YPos": -139,
          "ZPos": 276,
          "XRotation": 0,
          "YRotation": 0,
          "ZRotation": 0
        },
        {
          "ModelId": "41815",
          "ModelIdNum": 41815,
          "ObjectType": 0,
          "XPos": -106,
          "YPos": -135,
          "ZPos": 228,
          "XRotation": 0,
          "YRotation": -77,
          "ZRotation": 0
        },
        {
          "ModelId": "42071",
          "ModelIdNum": 42071,
          "ObjectType": 0,
          "XPos": 137,
          "YPos": -42,
          "ZPos": 110,
          "XRotation": 0,
          "YRotation": -1024,
          "ZRotation": 0
        }
      ],
      "BlockFlatObjectRecords": [
        {
          "Position": 0,
          "XPos": -8,
          "YPos": -80,
          "ZPos": -152,
          "TextureArchive": 210,
          "TextureRecord": 13,
          "FactionID": -32752,
          "Flags": 17
        },
        {
          "Position": 0,
          "XPos": -144,
          "YPos": -80,
          "ZPos": 256,
          "TextureArchive": 210,
          "TextureRecord": 13,
          "FactionID": 28684,
          "Flags": 17
        },
        {
          "Position": 0,
          "XPos": 100,
          "YPos": 0,
          "ZPos": 158,
          "TextureArchive": 199,
          "TextureRecord": 20,
          "FactionID": 0,
          "Flags": 17
        },
        {
          "Position": 0,
          "XPos": 86,
          "YPos": 0,
          "ZPos": -164,
          "TextureArchive": 199,
          "TextureRecord": 20,
          "FactionID": 0,
          "Flags": 17
        },
        {
          "Position": 0,
          "XPos": -136,
          "YPos": 0,
          "ZPos": 258,
          "TextureArchive": 199,
          "TextureRecord": 20,
          "FactionID": 0,
          "Flags": 17
        },
        {
          "Position": 0,
          "XPos": -104,
          "YPos": -129,
          "ZPos": -160,
          "TextureArchive": 199,
          "TextureRecord": 20,
          "FactionID": 0,
          "Flags": 17
        },
        {
          "Position": 0,
          "XPos": 0,
          "YPos": -215,
          "ZPos": -40,
          "TextureArchive": 210,
          "TextureRecord": 25,
          "FactionID": -32752,
          "Flags": 17
        },
        {
          "Position": 0,
          "XPos": 32,
          "YPos": -129,
          "ZPos": 168,
          "TextureArchive": 199,
          "TextureRecord": 22,
          "FactionID": 0,
          "Flags": 17
        },
        {
          "Position": 0,
          "XPos": 128,
          "YPos": 0,
          "ZPos": 264,
          "TextureArchive": 199,
          "TextureRecord": 21,
          "FactionID": 0,
          "Flags": 17
        },
        {
          "Position": 0,
          "XPos": 128,
          "YPos": 0,
          "ZPos": 0,
          "TextureArchive": 199,
          "TextureRecord": 8,
          "FactionID": 0,
          "Flags": 0
        },
        {
          "Position": 0,
          "XPos": -23,
          "YPos": -35,
          "ZPos": -254,
          "TextureArchive": 10021,
          "TextureRecord": 6,
          "FactionID": 0,
          "Flags": 0
        },
        {
          "Position": 0,
          "XPos": -3,
          "YPos": -34,
          "ZPos": -238,
          "TextureArchive": 10021,
          "TextureRecord": 4,
          "FactionID": 0,
          "Flags": 0
        },
        {
          "Position": 0,
          "XPos": -40,
          "YPos": -35,
          "ZPos": -237,
          "TextureArchive": 10021,
          "TextureRecord": 17,
          "FactionID": 0,
          "Flags": 0
        },
        {
          "Position": 0,
          "XPos": 5,
          "YPos": -35,
          "ZPos": -260,
          "TextureArchive": 1210,
          "TextureRecord": 11,
          "FactionID": 0,
          "Flags": 0
        },
        {
          "Position": 0,
          "XPos": 158,
          "YPos": -1,
          "ZPos": 32,
          "TextureArchive": 204,
          "TextureRecord": 2,
          "FactionID": 0,
          "Flags": 0
        },
        {
          "Position": 0,
          "XPos": 0,
          "YPos": -8,
          "ZPos": 162,
          "TextureArchive": 199,
          "TextureRecord": 11,
          "FactionID": 0,
          "Flags": 0
        },
        {
          "Position": 0,
          "XPos": 114,
          "YPos": -18,
          "ZPos": 108,
          "TextureArchive": 199,
          "TextureRecord": 4,
          "FactionID": 0,
          "Flags": 0
        },
        {
          "Position": 0,
          "XPos": 71,
          "YPos": -1,
          "ZPos": -140,
          "TextureArchive": 199,
          "TextureRecord": 18,
          "FactionID": 0,
          "Flags": 0
        }
      ],
      "BlockSection3Records": [
        {
          "XPos": -128,
          "YPos": 0,
          "ZPos": 256
        },
        {
          "XPos": 0,
          "YPos": 0,
          "ZPos": 256
        },
        {
          "XPos": -128,
          "YPos": 0,
          "ZPos": 128
        },
        {
          "XPos": 0,
          "YPos": 0,
          "ZPos": 128
        },
        {
          "XPos": 128,
          "YPos": 0,
          "ZPos": 128
        },
        {
          "XPos": 0,
          "YPos": 0,
          "ZPos": 0
        },
        {
          "XPos": -128,
          "YPos": 0,
          "ZPos": 0
        },
        {
          "XPos": -128,
          "YPos": 0,
          "ZPos": -128
        },
        {
          "XPos": 0,
          "YPos": 0,
          "ZPos": -128
        },
        {
          "XPos": 128,
          "YPos": 0,
          "ZPos": -128
        },
        {
          "XPos": 128,
          "YPos": 0,
          "ZPos": -256
        },
        {
          "XPos": 0,
          "YPos": 0,
          "ZPos": -256
        },
        {
          "XPos": -128,
          "YPos": 0,
          "ZPos": -256
        },
        {
          "XPos": -128,
          "YPos": -129,
          "ZPos": 256
        },
        {
          "XPos": 0,
          "YPos": -129,
          "ZPos": 256
        },
        {
          "XPos": 0,
          "YPos": -129,
          "ZPos": 128
        },
        {
          "XPos": 128,
          "YPos": -129,
          "ZPos": 128
        },
        {
          "XPos": 128,
          "YPos": -129,
          "ZPos": 0
        },
        {
          "XPos": 0,
          "YPos": -129,
          "ZPos": 0
        },
        {
          "XPos": 0,
          "YPos": -129,
          "ZPos": -128
        },
        {
          "XPos": 128,
          "YPos": -129,
          "ZPos": -128
        },
        {
          "XPos": 128,
          "YPos": -129,
          "ZPos": -256
        },
        {
          "XPos": 0,
          "YPos": -129,
          "ZPos": -256
        },
        {
          "XPos": -128,
          "YPos": -129,
          "ZPos": -256
        },
        {
          "XPos": -128,
          "YPos": -129,
          "ZPos": -128
        },
        {
          "XPos": -128,
          "YPos": -129,
          "ZPos": 0
        },
        {
          "XPos": -128,
          "YPos": -129,
          "ZPos": 128
        },
        {
          "XPos": 128,
          "YPos": -129,
          "ZPos": 256
        }
      ],
      "BlockPeopleRecords": [
        {
          "Position": 3592,
          "XPos": -68,
          "YPos": 0,
          "ZPos": -18,
          "TextureArchive": 182,
          "TextureRecord": 47,
          "FactionID": 0,
          "Flags": 33
        },
        {
          "Position": 3593,
          "XPos": -132,
          "YPos": -1,
          "ZPos": -144,
          "TextureArchive": 182,
          "TextureRecord": 4,
          "FactionID": 0,
          "Flags": 0
        }
      ],
      "BlockDoorRecords": [
        {
          "Position": 0,
          "XPos": 71,
          "YPos": -45,
          "ZPos": 279,
          "YRotation": -512,
          "OpenRotation": 90,
          "DoorModelIndex": 0
        }
      ]
    }
  },
  "AutoMapData": null
}