{
    "FactionId": 0,
    "BuildingType": 18,
    "Quality": 7,
    "NameSeed": 0,
    "RmbSubRecord": {
        "XPos": 687,
        "ZPos": 2248,
        "YRotation": 0,
        "Exterior": {
            "Header": {
                "Num3dObjectRecords": 1,
                "NumFlatObjectRecords": 1,
                "NumSection3Records": 0,
                "NumPeopleRecords": 0,
                "NumDoorRecords": 0
            },
            "Block3dObjectRecords": [
                {
                    "ModelId": "610",
                    "ModelIdNum": 610,
                    "ObjectType": 4,
                    "XPos": 0,
                    "YPos": 1,
                    "ZPos": 0,
                    "XRotation": 0,
                    "YRotation": 0,
                    "ZRotation": 0
                }
            ],
            "BlockFlatObjectRecords": [
                {
                    "Position": 9864,
                    "XPos": 2240,
                    "YPos": -8,
                    "ZPos": -448,
                    "TextureArchive": 199,
                    "TextureRecord": 8,
                    "FactionID": 0,
                    "Flags": 0
                }
            ],
            "BlockSection3Records": [],
            "BlockPeopleRecords": [],
            "BlockDoorRecords": []
        },
        "Interior": {
            "Header": {
                "Num3dObjectRecords": 24,
                "NumFlatObjectRecords": 5,
                "NumSection3Records": 4,
                "NumPeopleRecords": 1,
                "NumDoorRecords": 2
            },
            "Block3dObjectRecords": [
                {
                    "ModelId": "8700",
                    "ModelIdNum": 8700,
                    "ObjectType": 13,
                    "XPos": 61,
                    "YPos": -63,
                    "ZPos": -128,
                    "XRotation": 0,
                    "YRotation": 512,
                    "ZRotation": 0
                },
                {
                    "ModelId": "8700",
                    "ModelIdNum": 8700,
                    "ObjectType": 13,
                    "XPos": 61,
                    "YPos": -63,
                    "ZPos": 0,
                    "XRotation": 0,
                    "YRotation": 512,
                    "ZRotation": 0
                },
                {
                    "ModelId": "3700",
                    "ModelIdNum": 3700,
                    "ObjectType": 13,
                    "XPos": -3,
                    "YPos": -64,
                    "ZPos": 0,
                    "XRotation": 0,
                    "YRotation": 0,
                    "ZRotation": 0
                },
                {
                    "ModelId": "3700",
                    "ModelIdNum": 3700,
                    "ObjectType": 13,
                    "XPos": -3,
                    "YPos": -64,
                    "ZPos": -128,
                    "XRotation": 0,
                    "YRotation": 0,
                    "ZRotation": 0
                },
                {
                    "ModelId": "3704",
                    "ModelIdNum": 3704,
                    "ObjectType": 13,
                    "XPos": 64,
                    "YPos": -64,
                    "ZPos": 70,
                    "XRotation": 0,
                    "YRotation": 1536,
                    "ZRotation": 0
                },
                {
                    "ModelId": "3704",
                    "ModelIdNum": 3704,
                    "ObjectType": 13,
                    "XPos": 122,
                    "YPos": -64,
                    "ZPos": 128,
                    "XRotation": 0,
                    "YRotation": 0,
                    "ZRotation": 0
                },
                {
                    "ModelId": "3719",
                    "ModelIdNum": 3719,
                    "ObjectType": 13,
                    "XPos": 0,
                    "YPos": -64,
                    "ZPos": 186,
                    "XRotation": 0,
                    "YRotation": 512,
                    "ZRotation": 0
                },
                {
                    "ModelId": "4700",
                    "ModelIdNum": 4700,
                    "ObjectType": 13,
                    "XPos": 0,
                    "YPos": -64,
                    "ZPos": 71,
                    "XRotation": 0,
                    "YRotation": 1024,
                    "ZRotation": 0
                },
                {
                    "ModelId": "4700",
                    "ModelIdNum": 4700,
                    "ObjectType": 13,
                    "XPos": -7,
                    "YPos": -64,
                    "ZPos": -64,
                    "XRotation": 0,
                    "YRotation": 1536,
                    "ZRotation": 0
                },
                {
                    "ModelId": "3719",
                    "ModelIdNum": 3719,
                    "ObjectType": 13,
                    "XPos": -122,
                    "YPos": -64,
                    "ZPos": 64,
                    "XRotation": 0,
                    "YRotation": 1024,
                    "ZRotation": 0
                },
                {
                    "ModelId": "3730",
                    "ModelIdNum": 3730,
                    "ObjectType": 13,
                    "XPos": -64,
                    "YPos": -64,
                    "ZPos": -186,
                    "XRotation": 0,
                    "YRotation": 1536,
                    "ZRotation": 0
                },
                {
                    "ModelId": "3702",
                    "ModelIdNum": 3702,
                    "ObjectType": 13,
                    "XPos": -122,
                    "YPos": -64,
                    "ZPos": -128,
                    "XRotation": 0,
                    "YRotation": 1024,
                    "ZRotation": 0
                },
                {
                    "ModelId": "4700",
                    "ModelIdNum": 4700,
                    "ObjectType": 13,
                    "XPos": -121,
                    "YPos": -64,
                    "ZPos": -64,
                    "XRotation": 0,
                    "YRotation": 512,
                    "ZRotation": 0
                },
                {
                    "ModelId": "4700",
                    "ModelIdNum": 4700,
                    "ObjectType": 13,
                    "XPos": -7,
                    "YPos": -64,
                    "ZPos": 64,
                    "XRotation": 0,
                    "YRotation": 1536,
                    "ZRotation": 0
                },
                {
                    "ModelId": "2000",
                    "ModelIdNum": 2000,
                    "ObjectType": 13,
                    "XPos": 64,
                    "YPos": -128,
                    "ZPos": 127,
                    "XRotation": 0,
                    "YRotation": 0,
                    "ZRotation": 0
                },
                {
                    "ModelId": "2002",
                    "ModelIdNum": 2002,
                    "ObjectType": 13,
                    "XPos": -64,
                    "YPos": -128,
                    "ZPos": -1,
                    "XRotation": 0,
                    "YRotation": 0,
                    "ZRotation": 0
                },
                {
                    "ModelId": "1002",
                    "ModelIdNum": 1002,
                    "ObjectType": 13,
                    "XPos": -64,
                    "YPos": 0,
                    "ZPos": 0,
                    "XRotation": 0,
                    "YRotation": 0,
                    "ZRotation": 0
                },
                {
                    "ModelId": "1000",
                    "ModelIdNum": 1000,
                    "ObjectType": 5,
                    "XPos": 64,
                    "YPos": 0,
                    "ZPos": 128,
                    "XRotation": 0,
                    "YRotation": 0,
                    "ZRotation": 0
                },
                {
                    "ModelId": "41000",
                    "ModelIdNum": 41000,
                    "ObjectType": 3,
                    "XPos": 80,
                    "YPos": 2,
                    "ZPos": 8,
                    "XRotation": 0,
                    "YRotation": 0,
                    "ZRotation": 0
                },
                {
                    "ModelId": "41000",
                    "ModelIdNum": 41000,
                    "ObjectType": 3,
                    "XPos": 80,
                    "YPos": 2,
                    "ZPos": -128,
                    "XRotation": 0,
                    "YRotation": 0,
                    "ZRotation": 0
                },
                {
                    "ModelId": "41029",
                    "ModelIdNum": 41029,
                    "ObjectType": 3,
                    "XPos": 104,
                    "YPos": 2,
                    "ZPos": 128,
                    "XRotation": 0,
                    "YRotation": 513,
                    "ZRotation": 0
                },
                {
                    "ModelId": "41116",
                    "ModelIdNum": 41116,
                    "ObjectType": 3,
                    "XPos": -64,
                    "YPos": 2,
                    "ZPos": 168,
                    "XRotation": 0,
                    "YRotation": 1025,
                    "ZRotation": 0
                },
                {
                    "ModelId": "41106",
                    "ModelIdNum": 41106,
                    "ObjectType": 3,
                    "XPos": -104,
                    "YPos": 2,
                    "ZPos": 88,
                    "XRotation": 0,
                    "YRotation": 1537,
                    "ZRotation": 0
                },
                {
                    "ModelId": "41102",
                    "ModelIdNum": 41102,
                    "ObjectType": 3,
                    "XPos": -16,
                    "YPos": 2,
                    "ZPos": 120,
                    "XRotation": 0,
                    "YRotation": 450,
                    "ZRotation": 0
                }
            ],
            "BlockFlatObjectRecords": [
                {
                    "Position": 11482,
                    "XPos": -48,
                    "YPos": 0,
                    "ZPos": 64,
                    "TextureArchive": 199,
                    "TextureRecord": 20,
                    "FactionID": 0,
                    "Flags": 17
                },
                {
                    "Position": 11499,
                    "XPos": 48,
                    "YPos": -80,
                    "ZPos": 128,
                    "TextureArchive": 210,
                    "TextureRecord": 13,
                    "FactionID": -32752,
                    "Flags": 17
                },
                {
                    "Position": 11516,
                    "XPos": -80,
                    "YPos": -80,
                    "ZPos": -64,
                    "TextureArchive": 210,
                    "TextureRecord": 13,
                    "FactionID": 28680,
                    "Flags": 17
                },
                {
                    "Position": 11533,
                    "XPos": -64,
                    "YPos": 0,
                    "ZPos": -128,
                    "TextureArchive": 199,
                    "TextureRecord": 8,
                    "FactionID": 0,
                    "Flags": 0
                },
                {
                    "Position": 11550,
                    "XPos": 64,
                    "YPos": 0,
                    "ZPos": 128,
                    "TextureArchive": 199,
                    "TextureRecord": 8,
                    "FactionID": 0,
                    "Flags": 0
                }
            ],
            "BlockSection3Records": [
                {
                    "XPos": -64,
                    "YPos": 0,
                    "ZPos": 0
                },
                {
                    "XPos": -64,
                    "YPos": 0,
                    "ZPos": 128
                },
                {
                    "XPos": 64,
                    "YPos": 0,
                    "ZPos": 0
                },
                {
                    "XPos": 64,
                    "YPos": 0,
                    "ZPos": -128
                }
            ],
            "BlockPeopleRecords": [
                {
                    "Position": 11631,
                    "XPos": 72,
                    "YPos": -16,
                    "ZPos": -128,
                    "TextureArchive": 184,
                    "TextureRecord": 12,
                    "FactionID": 0,
                    "Flags": 33
                }
            ],
            "BlockDoorRecords": [
                {
                    "Position": 11648,
                    "XPos": 7,
                    "YPos": -45,
                    "ZPos": -105,
                    "YRotation": 1536,
                    "OpenRotation": 92,
                    "DoorModelIndex": 0
                },
                {
                    "Position": 11667,
                    "XPos": 7,
                    "YPos": -45,
                    "ZPos": 23,
                    "YRotation": 1536,
                    "OpenRotation": 92,
                    "DoorModelIndex": 0
                }
            ]
        }
    },
    "AutoMapData": null
}